bbref_team_game_logs/__init__.py
bbref_team_game_logs/bbref_team_game_logs.py
bbref_team_game_logs-1.0.3.dist-info/LICENSE
bbref_team_game_logs-1.0.3.dist-info/METADATA
bbref_team_game_logs-1.0.3.dist-info/WHEEL
bbref_team_game_logs-1.0.3.dist-info/top_level.txt
bbref_team_game_logs-1.0.3.dist-info/RECORD
