Metadata-Version: 2.1
Name: bbref-team-game-logs
Version: 1.0.3
Summary: Retrieves a team's regular season game log and stats
Home-page: https://github.com/sherpan/bbref_team_game_logs
Author: Siddharth Mehta
Author-email: siddharthm2350@gmail.com
License: UNKNOWN
Platform: UNKNOWN
Classifier: Programming Language :: Python :: 3
Classifier: License :: OSI Approved :: MIT License
Classifier: Operating System :: OS Independent
Requires-Python: >=3.6
Requires-Dist: beautifulsoup4 (==4.8.2)
Requires-Dist: pandas (==0.25.3)
Requires-Dist: requests (==2.22.0)
Requires-Dist: lxml (==4.4.2)
